AUTHORS
CHANGELOG.txt
DESCRIPTION
LICENSE
MANIFEST.in
README.rst
setup.py
asiapay/__init__.py
asiapay/admin.py
asiapay/models.py
asiapay/urls.py
asiapay/views.py
asiapay/migrations/0001_initial.py
asiapay/migrations/0002_auto_20160804_1459.py
asiapay/migrations/__init__.py
asiapay/south_migrations/0001_initial.py
asiapay/south_migrations/0002_auto__chg_field_asiapaytransaction_bank_reference.py
asiapay/south_migrations/0003_auto__chg_field_asiapaytransaction_transaction_time.py
asiapay/south_migrations/0004_auto__chg_field_asiapaytransaction_merchant_id.py
asiapay/south_migrations/0005_auto__chg_field_asiapaytransaction_exp_year__chg_field_asiapaytransact.py
asiapay/south_migrations/0006_auto__chg_field_asiapaytransaction_merchant_id__chg_field_asiapaytrans.py
asiapay/south_migrations/__init__.py
asiapay/templates/asiapay/payment.html
asiapay/templates/asiapay/dashboard/transaction_detail.html
asiapay/templates/asiapay/dashboard/transaction_list.html
asiapay/tests/__init__.py
asiapay/tests/factories.py
asiapay/tests/models_tests.py
asiapay/tests/runtests.py
asiapay/tests/settings.py
asiapay/tests/test_settings.py
asiapay/tests/urls.py
asiapay/tests/views_tests.py
django_oscar_asiapay.egg-info/PKG-INFO
django_oscar_asiapay.egg-info/SOURCES.txt
django_oscar_asiapay.egg-info/dependency_links.txt
django_oscar_asiapay.egg-info/requires.txt
django_oscar_asiapay.egg-info/top_level.txt