Metadata-Version: 1.0
Name: django-oscar-asiapay
Version: 0.4.0
Summary: Payment integration of AsiaPay (PayDollar) to use on django-oscar
